market_data_api/MarketDataAPI.py
market_data_api/__init__.py
market_data_api-0.0.1.dist-info/LICENSE.txt
market_data_api-0.0.1.dist-info/METADATA
market_data_api-0.0.1.dist-info/WHEEL
market_data_api-0.0.1.dist-info/top_level.txt
market_data_api-0.0.1.dist-info/RECORD
