Metadata-Version: 2.1
Name: market-data-api
Version: 0.0.1
Summary: Python SDK for working with the MarketData APIs
Home-page: https://github.com/guruappa/MarketDataApp
Author: Guruppa Padsali
Author-email: guruappa@gmail.com
License: MIT
Classifier: Development Status :: 1 - Planning
Classifier: Environment :: Console
Classifier: Intended Audience :: Financial and Insurance Industry
Classifier: License :: OSI Approved :: MIT License
Classifier: Natural Language :: English
Classifier: Operating System :: POSIX :: Linux
Classifier: Programming Language :: Python :: Implementation
Classifier: Topic :: Office/Business :: Financial :: Investment
License-File: LICENSE.txt
